nim_python_package/__init__.py
nim_python_package/__main__.py
nim_python_package/sub_module/__init__.py
nim_python_package/sub_module/just_a_test.py
nim_python_package-10.1.1.dist-info/LICENSE
nim_python_package-10.1.1.dist-info/WHEEL
nim_python_package-10.1.1.dist-info/METADATA
nim_python_package-10.1.1.dist-info/RECORD
