Metadata-Version: 2.1
Name: nim_python_package
Version: 10.1.1
Summary: A min testing package.
Author-email: Sander Teunissen <sander.teunissen@alliander.com>
Requires-Python: >=3.7
Classifier: License :: OSI Approved :: MIT License
Requires-Dist: requests
Requires-Dist: pre-commit ; extra == "develop"
Requires-Dist: mypy ; extra == "develop"
Requires-Dist: flake8 ; extra == "develop"
Requires-Dist: pylint==2.12.2 ; extra == "develop"
Requires-Dist: invoke ; extra == "develop"
Requires-Dist: build ; extra == "develop"
Requires-Dist: pytest ; extra == "test"
Requires-Dist: pylint==2.12.2 ; extra == "test"
Requires-Dist: coverage[toml] ; extra == "test"
Provides-Extra: develop
Provides-Extra: test
